Taweret/__init__.py
Taweret/test.py
Taweret/core/__init__.py
Taweret/core/base_mixer.py
Taweret/core/base_model.py
Taweret/mix/__init__.py
Taweret/mix/bivariate_linear.py
Taweret/mix/gaussian.py
Taweret/mix/trees.py
Taweret/models/__init__.py
Taweret/models/coleman_models.py
Taweret/models/polynomial_models.py
Taweret/models/samba_models.py
Taweret/sampler/__init__.py
Taweret/sampler/likelihood_wrappers.py
Taweret/tests/__init__.py
Taweret/tests/samba_results.txt
Taweret/tests/test_bivariate_linear.py
Taweret/tests/test_gaussian.py
Taweret/tests/test_trees.py
Taweret/tests/bart_bmm_test_data/2d_pmean.txt
Taweret/tests/bart_bmm_test_data/2d_wmean.txt
Taweret/tests/bart_bmm_test_data/2d_x_test.txt
Taweret/tests/bart_bmm_test_data/2d_x_train.txt
Taweret/tests/bart_bmm_test_data/2d_y_train.txt
Taweret/utils/__init__.py
Taweret/utils/priors.py
Taweret/utils/utils.py
Taweret-1.1.0.dist-info/LICENSE
Taweret-1.1.0.dist-info/METADATA
Taweret-1.1.0.dist-info/WHEEL
Taweret-1.1.0.dist-info/top_level.txt
Taweret-1.1.0.dist-info/RECORD
