Metadata-Version: 2.1
Name: Taweret
Version: 1.1.0
Summary: A python package for Bayesian model mixing
Author-email: Kevin Ingles <kingles@illinois.edu>, "Dananjaya (Dan) Liyanage" <liyanage@osu.edu>, Alexandra Semposki <as727414@ohio.edu>, John Yannotty <yannotty.1@buckeyemail.osu.edu>
License: MIT License
Classifier: License :: OSI Approved :: MIT License
Classifier: Operating System :: OS Independent
Classifier: Programming Language :: Python
Classifier: Programming Language :: Python :: 3
Classifier: Intended Audience :: Science/Research
Requires-Python: >=3.9
License-File: LICENSE
Requires-Dist: numpy >=1.20.3
Requires-Dist: matplotlib
Requires-Dist: scipy >=1.7.0
Requires-Dist: bilby
Requires-Dist: pytest
Requires-Dist: openbtmixing
